[
  {
    "id": "listView1",
    "component": "ListView",
    "attributes": {
      "bindConnectMetadata": {},
      "connectorMethod": {},
      ":dataSourceData": "$w.page.dataset.state.chargeOrderRecords",
      "dataSourceType": "expression",
      "datasource": {
        "name": "sys_user",
        "type": "datamodal"
      },
      "emptyText": "暂无数据",
      "enableTotal": false,
      "exprToFieldsSchema": "ff0bf181",
      "isSetStatus": true,
      "isSupportApis": false,
      "loadCompletedText": "",
      "orderType": "asc",
      "pageSize": 5,
      "pagination": "loadMoreButton",
      ":queryCondition": "[{\n  \"$and\": [{\n    \"$and\": [{\n      \"type\": {\n        \"$eq\": 0\n      }\n    }]\n  }]\n}]",
      "template": "simpleList",
      "style": {
        "padding": "8PX 16PX"
      }
    },
    "items": [
      {
        "id": "repeater2",
        "component": "Repeater",
        "attributes": {
          ":data": "$w.listView1.records",
          "forIndex": "index_listView1",
          "forItem": "item_listView1",
          "key": "_id",
          "suffix": "listView1"
        },
        "items": [
          {
            "id": "container4",
            "component": "Container",
            "attributes": {
              "data": {},
              "style": {
                "width": "100%",
                "display": "flex",
                "padding": "12PX 0PX",
                "position": "relative",
                "boxSizing": "border-box",
                "alignItems": "center",
                "borderBottom": "1px solid var(--wd-color-border-separator)"
              }
            },
            "items": [
              {
                "id": "container5",
                "component": "Container",
                "attributes": {
                  "data": {},
                  "style": {
                    "gap": "4PX",
                    "flex": "1",
                    "display": "flex",
                    "wordBreak": "break-all",
                    "alignItems": "flex-start",
                    "flexDirection": "column"
                  }
                },
                "items": [
                  {
                    "id": "text3",
                    "component": "WdText",
                    "attributes": {
                      "level": "title-8",
                      "maxLines": "1",
                      ":text": "$w.item_listView1.name"
                    },
                    "directives": {
                      ":if": true
                    },
                    "extra": {
                      "attributeExtraData": {}
                    }
                  },
                  {
                    "id": "text1",
                    "component": "WdText",
                    "attributes": {
                      "maxLines": "1",
                      ":text": "$w.DateText($w.item_listView1.createdAt, 'YYYY-MM-DD HH:mm:ss')",
                      "style": {
                        "color": "rgba(0, 0, 0, 0.5)",
                        "fontSize": "12"
                      }
                    },
                    "directives": {
                      ":if": true
                    },
                    "extra": {
                      "attributeExtraData": {}
                    }
                  }
                ],
                "directives": {
                  ":if": true
                },
                "extra": {
                  "attributeExtraData": {}
                }
              },
              {
                "id": "container6",
                "component": "Container",
                "attributes": {
                  "data": {},
                  "style": {
                    "color": "var(--wd-color-text-default)",
                    "width": "40PX",
                    "height": "24PX",
                    "margin": "undefined undefined undefined 16PX",
                    "display": "flex",
                    "opacity": 0.9,
                    "alignItems": "center",
                    "marginLeft": "16PX",
                    "justifyContent": "center"
                  }
                },
                "items": [
                  {
                    "id": "text4",
                    "component": "WdText",
                    "attributes": {
                      "level": "body-sm",
                      "maxLines": "1",
                      "overflow": true,
                      ":text": "'¥' + $w.item_listView1.actual_price / 100",
                      "style": {
                        "color": "var(--wd-color-text-placeholder)"
                      }
                    },
                    "directives": {
                      ":if": true
                    },
                    "extra": {
                      "attributeExtraData": {}
                    }
                  }
                ],
                "directives": {
                  ":if": true
                },
                "extra": {
                  "attributeExtraData": {}
                }
              }
            ],
            "directives": {
              ":if": true
            },
            "extra": {
              "attributeExtraData": {}
            }
          }
        ],
        "directives": {
          ":if": true
        },
        "extra": {
          "attributeExtraData": {}
        }
      }
    ],
    "directives": {
      ":if": true
    },
    "extra": {
      "attributeExtraData": {}
    }
  }
]